glossapi/__init__.py
glossapi/corpus.py
glossapi/gloss_downloader.py
glossapi/gloss_extract.py
glossapi/gloss_section.py
glossapi/gloss_section_classifier.py
glossapi/parquet_schema.py
glossapi/sampler.py
glossapi/models/kmeans_weights.joblib
glossapi/models/section_classifier.joblib
glossapi-0.0.13.dist-info/METADATA
glossapi-0.0.13.dist-info/WHEEL
glossapi-0.0.13.dist-info/top_level.txt
glossapi-0.0.13.dist-info/RECORD
