Metadata-Version: 2.4
Name: glossapi
Version: 0.0.13
Summary: A library for processing academic texts in Greek and other languages
Author-email: GlossAPI Team <foivos@example.com>
License: European Union Public Licence 1.2 (EUPL 1.2)
Project-URL: Repository, https://github.com/eellak/glossAPI
Classifier: Programming Language :: Python :: 3
Classifier: License :: OSI Approved :: European Union Public Licence 1.2 (EUPL 1.2)
Classifier: Operating System :: OS Independent
Classifier: Development Status :: 3 - Alpha
Requires-Python: >=3.8
Requires-Dist: docling
Requires-Dist: pandas
Requires-Dist: numpy
Requires-Dist: scikit-learn
Requires-Dist: joblib
Requires-Dist: dask
Requires-Dist: pyarrow
Requires-Dist: ftfy
Requires-Dist: tenacity
Requires-Dist: aiohttp
Requires-Dist: aiofiles
